thrift_fmt/__init__.py
thrift_fmt/core.py
thrift_fmt/main.py
thrift_fmt-0.3.0.dist-info/entry_points.txt
thrift_fmt-0.3.0.dist-info/WHEEL
thrift_fmt-0.3.0.dist-info/METADATA
thrift_fmt-0.3.0.dist-info/licenses/LICENSE
thrift_fmt-0.3.0.dist-info/RECORD
